{
  "sources": [
    {
      "title": "The Defiant",
      "feedUrl": "https://thedefiant.io/feed/",
      "siteUrl": "https://thedefiant.io",
      "articles": [
        {
          "id": "https://thedefiant.io/?p=54108",
          "author": "Samuel Haig",
          "description": "DeFi Purists Doubt THORWallet's non-KYC Claims",
          "link": "https://thedefiant.io/crypto-wallet-credit-card-transfer/",
          "publishedOn": "2022-06-28T08:51:05.000Z",
          "wordCount": 2396,
          "title": "DEX Lets Customers Make $100,000 Transfers with No Identity Check",
          "imageUrl": "https://thedefiant.io/wp-content/webpc-passthru.php?src=http://thedefiant.io/wp-content/uploads/2022/06/ThorWalletKYCLessOnRamp.jpg&nocache=1"
        },
        {
          "id": "https://thedefiant.io/?p=54096",
          "author": "Samuel Haig",
          "description": "Exchange Suspended Withdrawals June 23 Amid Liquidity Crunch",
          "link": "https://thedefiant.io/coinflex-bailout-whale/",
          "publishedOn": "2022-06-28T08:12:45.000Z",
          "wordCount": 2662,
          "title": "CoinFLEX Sets $47M Token Sale to Save Itself From Sinking Whale",
          "imageUrl": "https://thedefiant.io/wp-content/webpc-passthru.php?src=http://thedefiant.io/wp-content/uploads/2022/06/CoinFlexCoinOfferingAfterSuspendingWithdrawals.jpg&nocache=1"
        },
        {
          "id": "https://thedefiant.io/?p=54093",
          "author": "Robin Schmidt",
          "description": "Yes, we’re back from New York City and back into the grind of a market that has recovered a smidge of its dignity, total cryptocurrency market cap poking its head back above a trillion once again. For how long, well we’ll have to see. And with no prospect of the Fed easing off on rate …\n  Harmony Hacked, Yuga Strikes, Blockfi on the Rocks Read More »",
          "link": "https://thedefiant.io/harmony-hacked-yuga-strikes-blockfi-on-the-rocks/",
          "publishedOn": "2022-06-28T03:55:00.000Z",
          "wordCount": 2126,
          "title": "Harmony Hacked, Yuga Strikes, Blockfi on the Rocks",
          "imageUrl": "https://thedefiant.io/wp-content/webpc-passthru.php?src=http://thedefiant.io/wp-content/uploads/2022/06/Harmony-Hacked-Yuga-Strikes-Blockfi-on-the-Rocks.jpg&nocache=1"
        },
        {
          "id": "https://thedefiant.io/?p=54084",
          "author": "Owen Fernau",
          "description": "Solana Labs is dedicating a large part of its team to building its mobile effort, according to an exclusive interview with the company’s head of communications.",
          "link": "https://thedefiant.io/solana-saga-phone-team/",
          "publishedOn": "2022-06-27T22:20:18.000Z",
          "wordCount": 2546,
          "title": "Solana Labs Has About 10 People Working on Its Saga Mobile Phone Solana said last week it plans to unveil a mobile phone",
          "imageUrl": "https://thedefiant.io/wp-content/webpc-passthru.php?src=http://thedefiant.io/wp-content/uploads/2022/06/SMSOSOM.jpeg&nocache=1"
        },
        {
          "id": "https://thedefiant.io/?p=54078",
          "author": "Jason Levin",
          "description": "Ethereum developers are all about NFTs now, at least if the latest ETHNewYork is a good indication.",
          "link": "https://thedefiant.io/ethny-hackathon-winner/",
          "publishedOn": "2022-06-27T20:38:18.000Z",
          "wordCount": 2478,
          "title": "Ethereum Developers Were All About NFTs at ETHNewYork The top five finalists for ETHNewYork were all NFT-focused projects.",
          "imageUrl": "https://thedefiant.io/wp-content/webpc-passthru.php?src=http://thedefiant.io/wp-content/uploads/2022/06/ETHNYHackathon.jpeg&nocache=1"
        }
      ]
    }
  ],
  "cliVersion": "1.15.1"
}