{
  "sources": [
    {
      "title": "The Defiant",
      "feedUrl": "https://thedefiant.io/feed/",
      "siteUrl": "https://thedefiant.io",
      "articles": [
        {
          "id": "https://thedefiant.io/?p=51846",
          "author": "Aleksandar Gilbert",
          "description": "Crypto markets have stabilized, ending a market free-fall that erased $693B from crypto’s market capitalization from May 5 to May 12. Crypto’s market capitalization fell from $1.81T on May 5 to lows of $1.12T on May 12. The market started to rise on Friday, and now rests at $1.28T, data from CoinMarketCap shows. The crash …\n  Crypto Markets Stabilize After $693B Sell-Off Read More »",
          "link": "https://thedefiant.io/crypto-markets-stabilize-after-sell-off/",
          "publishedOn": "2022-05-18T11:34:06.000Z",
          "wordCount": 702,
          "title": "Crypto Markets Stabilize After $693B Sell-Off",
          "imageUrl": "https://thedefiant.io/wp-content/webpc-passthru.php?src=https://thedefiant.io/wp-content/uploads/2021/09/CDT-LevrgdYieldFrm-1.jpg&nocache=1"
        },
        {
          "id": "https://thedefiant.io/?p=51835",
          "author": "Samuel Haig",
          "description": "Norway’s central bank is embracing Ethereum’s Layer 2 for its central bank digital currency (CBDC) pilot. On May 16, Nahmii, an Ethereum L2, announced it had been tapped by Norges bank to host the sandbox for the country’s national currency, the krone. Nahmii said in a statement that it will “build, maintain, and train Norges …\n  Norway’s Central Bank Taps Ethereum Layer 2 For CBDC Trial Read More »",
          "link": "https://thedefiant.io/norway-layer-2-eth-cbdc/",
          "publishedOn": "2022-05-18T09:39:27.000Z",
          "wordCount": 613,
          "title": "Norway’s Central Bank Taps Ethereum Layer 2 For CBDC Trial",
          "imageUrl": "https://thedefiant.io/wp-content/webpc-passthru.php?src=https://thedefiant.io/wp-content/uploads/2022/05/Webp.net-resizeimage-4.jpg&nocache=1"
        },
        {
          "id": "https://thedefiant.io/?p=51822",
          "author": "Jason Levin",
          "description": "ConsenSys-backed VillageDAO will provide customer care services to other web3 projects – with the first client being Metamask.",
          "link": "https://thedefiant.io/consensys-villagedao/",
          "publishedOn": "2022-05-18T04:13:18.000Z",
          "wordCount": 667,
          "title": "VillageDAO Aims To Decentralize Customer Service",
          "imageUrl": "https://thedefiant.io/wp-content/webpc-passthru.php?src=https://thedefiant.io/wp-content/uploads/2022/05/VillageDAO.jpg&nocache=1"
        },
        {
          "id": "https://thedefiant.io/?p=51792",
          "author": "Owen Fernau",
          "description": "Robinhood will launch a Web3 wallet and plans to cover gas fees for users.",
          "link": "https://thedefiant.io/robinhood-web3-wallet/",
          "publishedOn": "2022-05-17T20:00:35.000Z",
          "wordCount": 661,
          "title": "Robinhood To Launch Non-Custodial Web3 Wallet The app plans to cover users' network fees.",
          "imageUrl": "https://thedefiant.io/wp-content/webpc-passthru.php?src=https://thedefiant.io/wp-content/uploads/2022/05/RobinhoodNonCustWallet.jpg&nocache=1"
        },
        {
          "id": "https://thedefiant.io/?p=51746",
          "author": "Samuel Haig",
          "description": "On May 16, Coinbase shared a wallet for its mobile app that lets customers access Ethereum-based dapps.",
          "link": "https://thedefiant.io/coinbase-ethereum-dapp/",
          "publishedOn": "2022-05-17T15:25:39.000Z",
          "wordCount": 524,
          "title": "Coinbase Rolls Out Ethereum Dapp Wallet",
          "imageUrl": "https://thedefiant.io/wp-content/webpc-passthru.php?src=https://thedefiant.io/wp-content/uploads/2022/05/CoinbaseDappsW3.jpeg&nocache=1"
        }
      ]
    }
  ],
  "cliVersion": "1.14.4"
}