{
  "sources": [
    {
      "title": "The Defiant",
      "feedUrl": "https://thedefiant.io/feed/",
      "siteUrl": "https://thedefiant.io/",
      "articles": [
        {
          "id": "https://thedefiant.io/?p=55370",
          "author": "Samuel Haig",
          "description": "Users Challenge SushiSwap's Claims It has First Cross-Chain AMM",
          "link": "https://thedefiant.io/sushiswap-cross-chain-amm/",
          "publishedOn": "2022-07-22T09:37:45.000Z",
          "wordCount": 2476,
          "title": "SushiSwap Triggers Dustup During Launch of Market Making Feature Users Challenge SushiSwap's Claims It has First Cross-Chain AMM",
          "imageUrl": "https://thedefiant.io/wp-content/webpc-passthru.php?src=http://thedefiant.io/wp-content/uploads/2022/07/sushixswap.jpg&nocache=1"
        },
        {
          "id": "https://thedefiant.io/?p=55355",
          "author": "yyctrader",
          "description": "A $150,000 Blunder and Revealed Oddities Round Out Another Busy Week in NFTs",
          "link": "https://thedefiant.io/minecraft-torpedoes-nfts-while-final-fantasy-forges-ahead/",
          "publishedOn": "2022-07-22T08:53:44.000Z",
          "wordCount": 2645,
          "title": "Minecraft Torpedoes NFTs While Final Fantasy Forges Ahead",
          "imageUrl": "https://thedefiant.io/wp-content/webpc-passthru.php?src=http://thedefiant.io/wp-content/uploads/2022/07/NFTRoundupMinecraft.jpg&nocache=1"
        },
        {
          "id": "https://thedefiant.io/?p=55266",
          "author": "IntoTheBlock",
          "description": "Stablecoin Yields Mirror Speculative and Deleveraging Cycles",
          "link": "https://thedefiant.io/intotheblock-stablecoin-yields-reveal-the-inner-workings-of-defi/",
          "publishedOn": "2022-07-22T05:36:10.000Z",
          "wordCount": 3179,
          "title": "IntoTheBlock: Stablecoin Yields Reveal the Inner Workings of DeFi Stablecoin Yields Mirror Speculative and Deleveraging Cycles",
          "imageUrl": "https://thedefiant.io/wp-content/webpc-passthru.php?src=http://thedefiant.io/wp-content/uploads/2022/07/DAOSJason.jpg&nocache=1"
        },
        {
          "id": "https://thedefiant.io/?p=55306",
          "author": "Aleksandar Gilbert",
          "description": "Ether held on exchanges has dropped 40% in the past year to 19M ETH.",
          "link": "https://thedefiant.io/eth-exchanges-4-year-low/",
          "publishedOn": "2022-07-22T01:16:03.000Z",
          "wordCount": 2410,
          "title": "Ether On Exchanges Plummets To 4-Year Low Ahead Of The Merge",
          "imageUrl": "https://thedefiant.io/wp-content/webpc-passthru.php?src=http://thedefiant.io/wp-content/uploads/2022/07/ethOnExchangesLow.jpg&nocache=1"
        },
        {
          "id": "https://thedefiant.io/?p=55300",
          "author": "Jason Levin",
          "description": "Former Coinbase product manager Ishan Wahi and two associates have been charged for allegedly front-running token listings.",
          "link": "https://thedefiant.io/coinbase-insider-trading/",
          "publishedOn": "2022-07-21T19:23:26.000Z",
          "wordCount": 2717,
          "title": "Feds Turn Up the Heat on Crypto with Insider Trading Case Against ex-Coinbase Employee SEC Defines 'Digital Assets' as Securities in Complaint",
          "imageUrl": "https://thedefiant.io/wp-content/webpc-passthru.php?src=http://thedefiant.io/wp-content/uploads/2022/07/CoinbaseInsiderTrading.jpg&nocache=1"
        }
      ]
    }
  ],
  "cliVersion": "1.15.1"
}