{
  "sources": [
    {
      "title": "The Defiant",
      "feedUrl": "https://thedefiant.io/feed/",
      "siteUrl": "https://thedefiant.io/",
      "articles": [
        {
          "id": "https://thedefiant.io/?p=57944",
          "author": "Owen Fernau",
          "description": "Users can subscribe to a Mirror publication with their crypto wallet and forward posts to their email.",
          "link": "https://thedefiant.io/mirror-web3-subscriptions/",
          "publishedOn": "2022-07-28T02:02:20.000Z",
          "wordCount": 2288,
          "title": "Web3 Publisher Takes a Page from TradFi with Subscription Model",
          "imageUrl": "https://the-defiant-web.s3.amazonaws.com/img/2022/07/27215911/MirrorL2.jpg"
        },
        {
          "id": "https://thedefiant.io/?p=57939",
          "author": "Aleksandar Gilbert",
          "description": "Global markets are rallying after the US central bank raised interest rates by 75 basis points in a widely expected move.",
          "link": "https://thedefiant.io/markets-rally-fed-hike/",
          "publishedOn": "2022-07-28T01:38:18.000Z",
          "wordCount": 2358,
          "title": "Markets Rally After Fed Hikes Rates By 0.75% The Central Bank Next Meets In September",
          "imageUrl": "https://the-defiant-web.s3.amazonaws.com/img/2022/07/27213605/FedRateHikeSparksCryptoRally.jpg"
        },
        {
          "id": "https://thedefiant.io/?p=57854",
          "author": "David Liebowitz",
          "description": "DeFi Dave Muses on Crucial Questions Confronting DeFi",
          "link": "https://thedefiant.io/ethcc-defi/",
          "publishedOn": "2022-07-27T18:29:14.000Z",
          "wordCount": 3465,
          "title": "EthCC Journal: Building Blocks for a Network State and a Decentralized Future Were Everywhere",
          "imageUrl": "https://the-defiant-web.s3.amazonaws.com/img/2022/07/27154757/ETHCCDive.jpg"
        },
        {
          "id": "https://thedefiant.io/?p=57910",
          "author": "Owen Fernau",
          "description": "Overlooked DEX Challenges Uniswap by Taking Four of Top 10 Places on Layer 2",
          "link": "https://thedefiant.io/velodrome-surging-uniswap/",
          "publishedOn": "2022-07-27T17:00:58.000Z",
          "wordCount": 2512,
          "title": "Velodrome Surprises Investors with Surge on Optimism Blockchain",
          "imageUrl": "https://the-defiant-web.s3.amazonaws.com/img/2022/07/27125809/VelodromeAirdrop.jpg"
        },
        {
          "id": "https://thedefiant.io/?p=57893",
          "author": "Aleksandar Gilbert",
          "description": "Users Decry 'Massive Supply Increase' of ONE Coins",
          "link": "https://thedefiant.io/harmony-strikes-discord-with-plan-to-mint-tokens-in-response-to-100m-hack/",
          "publishedOn": "2022-07-27T16:37:07.000Z",
          "wordCount": 2660,
          "title": "Harmony Strikes Discord With Plan to Mint Tokens in Response to $100M Hack Users Decry 'Massive Supply Increase' of ONE Coins",
          "imageUrl": "https://the-defiant-web.s3.amazonaws.com/img/2022/07/27153853/AngryMobHarmony.jpg"
        }
      ]
    }
  ],
  "cliVersion": "1.15.1"
}